ACKNOWLEDGEMENTS
AUTHORS
LICENSE
MANIFEST.in
README
dependencies.ini
pyproject.toml
requirements.txt
run_tests.py
setup.cfg
setup.py
test_requirements.txt
artifacts/__init__.py
artifacts/artifact.py
artifacts/definitions.py
artifacts/errors.py
artifacts/reader.py
artifacts/registry.py
artifacts/source_type.py
artifacts/writer.py
artifacts.egg-info/PKG-INFO
artifacts.egg-info/SOURCES.txt
artifacts.egg-info/dependency_links.txt
artifacts.egg-info/entry_points.txt
artifacts.egg-info/requires.txt
artifacts.egg-info/top_level.txt
artifacts/data/antivirus.yaml
artifacts/data/applications.yaml
artifacts/data/cloud_services.yaml
artifacts/data/config_files.yaml
artifacts/data/containerd.yaml
artifacts/data/database_servers.yaml
artifacts/data/docker.yaml
artifacts/data/esxi.yaml
artifacts/data/file_systems.yaml
artifacts/data/hadoop.yaml
artifacts/data/ics.yaml
artifacts/data/installed_module_paths.yaml
artifacts/data/installed_modules.yaml
artifacts/data/instant_messaging.yaml
artifacts/data/java.yaml
artifacts/data/kaspersky_careto.yaml
artifacts/data/kubernetes.yaml
artifacts/data/legacy.yaml
artifacts/data/linux.yaml
artifacts/data/linux_proc.yaml
artifacts/data/linux_services.yaml
artifacts/data/macos.yaml
artifacts/data/shell.yaml
artifacts/data/tomcat.yaml
artifacts/data/triage.yaml
artifacts/data/unix_common.yaml
artifacts/data/user.yaml
artifacts/data/webbrowser.yaml
artifacts/data/webservers.yaml
artifacts/data/windows.yaml
artifacts/data/windows_dll_hijacking.yaml
artifacts/data/wmi.yaml
artifacts/scripts/__init__.py
artifacts/scripts/stats.py
artifacts/scripts/validator.py
config/appveyor/install.ps1
config/appveyor/install.sh
config/appveyor/runtests.sh
config/dpkg/artifacts-data.dirs
config/dpkg/artifacts-data.install
config/dpkg/artifacts-tools.install
config/dpkg/changelog
config/dpkg/clean
config/dpkg/compat
config/dpkg/control
config/dpkg/copyright
config/dpkg/python3-artifacts.install
config/dpkg/rules
config/dpkg/source/format
test_data/definitions.json
test_data/definitions.yaml
tests/__init__.py
tests/reader_test.py
tests/registry_test.py
tests/source_type_test.py
tests/test_lib.py
tests/validator_test.py
tests/writer_test.py
utils/__init__.py
