Metadata-Version: 2.4
Name: artifacts
Version: 20250913
Summary: ForensicArtifacts.com Artifact Repository.
Home-page: https://github.com/ForensicArtifacts/artifacts
Maintainer: Forensic artifacts
Maintainer-email: forensicartifacts@googlegroups.com
License: Apache License, Version 2.0
Classifier: Development Status :: 3 - Alpha
Classifier: Programming Language :: Python
Requires-Python: >=3.8
License-File: ACKNOWLEDGEMENTS
License-File: AUTHORS
License-File: LICENSE
License-File: README
Requires-Dist: PyYAML>=3.10
Dynamic: license-file
